csrd_swaggerize/__init__.py
csrd_swaggerize/_utils/__init__.py
csrd_swaggerize/_utils/functions.py
csrd_swaggerize/config/__init__.py
csrd_swaggerize/config/swag_config.py
csrd_swaggerize/config/swag_contact.py
csrd_swaggerize/config/swag_info.py
csrd_swaggerize/config/swag_license.py
csrd_swaggerize/models/__init__.py
csrd_swaggerize/models/license.py
csrd_swaggerize/swaggerize.py
csrd_swaggerize-0.1.10.dist-info/METADATA
csrd_swaggerize-0.1.10.dist-info/WHEEL
csrd_swaggerize-0.1.10.dist-info/RECORD
